helpers/__init__.py
helpers/action_helper.py
helpers/cmd_helper.py
helpers/color_helper.py
helpers/debug_helper.py
helpers/emoji.py
helpers/exception_helper.py
helpers/file_helper.py
helpers/re_helper.py
helpers/static_global.py
helpers/thread_helper.py
helpers/time_helper.py
wings_easy-0.7.dist-info/licenses/LICENSE.txt
wings_easy-0.7.dist-info/METADATA
wings_easy-0.7.dist-info/WHEEL
wings_easy-0.7.dist-info/top_level.txt
wings_easy-0.7.dist-info/RECORD
